autogen/__init__.py
autogen/cli.py
autogen/client.py
autogen/config.py
autogen/database.py
autogen/runner.py
autogen/packages/__init__.py
autogen/packages/intercom.yml
autogen/packages/quickbooks.yml
autogen/packages/xero.yml
fivetran_autogen-0.0.1rc9.dist-info/METADATA
fivetran_autogen-0.0.1rc9.dist-info/WHEEL
fivetran_autogen-0.0.1rc9.dist-info/entry_points.txt
fivetran_autogen-0.0.1rc9.dist-info/top_level.txt
fivetran_autogen-0.0.1rc9.dist-info/RECORD
