Metadata-Version: 2.1
Name: fivetran-autogen
Version: 0.0.1rc9
Summary: UNKNOWN
Home-page: https://github.com/fivetran/dbt_autogen
Author: Fivetran
Author-email: hello@fivetran.com
License: UNKNOWN
Platform: UNKNOWN
Requires-Dist: click (==8.0.3)
Requires-Dist: google-cloud-bigquery (==2.32.0)
Requires-Dist: google-cloud-bigquery-storage (==2.11.0)
Requires-Dist: jsonschema (==4.4.0)
Requires-Dist: psycopg2 (==2.9.3)
Requires-Dist: pyarrow (==6.0.1)
Requires-Dist: PyYAML (==6.0)
Requires-Dist: requests (==2.27.1)
Requires-Dist: ruamel.yaml (==0.17.20)
Requires-Dist: snowflake-sqlalchemy (==1.3.3)
Requires-Dist: SQLAlchemy (==1.4.25)
Requires-Dist: sqlalchemy-bigquery (==1.3.0)
